azure/mgmt/devtestlabs/__init__.py
azure/mgmt/devtestlabs/_configuration.py
azure/mgmt/devtestlabs/_dev_test_labs_client.py
azure/mgmt/devtestlabs/version.py
azure/mgmt/devtestlabs/models/__init__.py
azure/mgmt/devtestlabs/models/_dev_test_labs_client_enums.py
azure/mgmt/devtestlabs/models/_models.py
azure/mgmt/devtestlabs/models/_models_py3.py
azure/mgmt/devtestlabs/models/_paged_models.py
azure/mgmt/devtestlabs/operations/__init__.py
azure/mgmt/devtestlabs/operations/_arm_templates_operations.py
azure/mgmt/devtestlabs/operations/_artifact_sources_operations.py
azure/mgmt/devtestlabs/operations/_artifacts_operations.py
azure/mgmt/devtestlabs/operations/_costs_operations.py
azure/mgmt/devtestlabs/operations/_custom_images_operations.py
azure/mgmt/devtestlabs/operations/_disks_operations.py
azure/mgmt/devtestlabs/operations/_environments_operations.py
azure/mgmt/devtestlabs/operations/_formulas_operations.py
azure/mgmt/devtestlabs/operations/_gallery_images_operations.py
azure/mgmt/devtestlabs/operations/_global_schedules_operations.py
azure/mgmt/devtestlabs/operations/_labs_operations.py
azure/mgmt/devtestlabs/operations/_notification_channels_operations.py
azure/mgmt/devtestlabs/operations/_operations.py
azure/mgmt/devtestlabs/operations/_policies_operations.py
azure/mgmt/devtestlabs/operations/_policy_sets_operations.py
azure/mgmt/devtestlabs/operations/_provider_operations.py
azure/mgmt/devtestlabs/operations/_schedules_operations.py
azure/mgmt/devtestlabs/operations/_secrets_operations.py
azure/mgmt/devtestlabs/operations/_service_fabric_schedules_operations.py
azure/mgmt/devtestlabs/operations/_service_fabrics_operations.py
azure/mgmt/devtestlabs/operations/_service_runners_operations.py
azure/mgmt/devtestlabs/operations/_users_operations.py
azure/mgmt/devtestlabs/operations/_virtual_machine_schedules_operations.py
azure/mgmt/devtestlabs/operations/_virtual_machines_operations.py
azure/mgmt/devtestlabs/operations/_virtual_networks_operations.py
azure_mgmt_devtestlabs-4.0.0.dist-info/METADATA
azure_mgmt_devtestlabs-4.0.0.dist-info/WHEEL
azure_mgmt_devtestlabs-4.0.0.dist-info/top_level.txt
azure_mgmt_devtestlabs-4.0.0.dist-info/RECORD
